huaweicloudsdkkps/__init__.py
huaweicloudsdkkps/v3/__init__.py
huaweicloudsdkkps/v3/kps_async_client.py
huaweicloudsdkkps/v3/kps_client.py
huaweicloudsdkkps/v3/model/__init__.py
huaweicloudsdkkps/v3/model/associate_keypair_request.py
huaweicloudsdkkps/v3/model/associate_keypair_request_body.py
huaweicloudsdkkps/v3/model/associate_keypair_response.py
huaweicloudsdkkps/v3/model/auth.py
huaweicloudsdkkps/v3/model/batch_associate_keypair_request.py
huaweicloudsdkkps/v3/model/batch_associate_keypair_request_body.py
huaweicloudsdkkps/v3/model/batch_associate_keypair_response.py
huaweicloudsdkkps/v3/model/batch_export_private_key_request.py
huaweicloudsdkkps/v3/model/batch_export_private_key_response.py
huaweicloudsdkkps/v3/model/batch_import_keypair_request.py
huaweicloudsdkkps/v3/model/batch_import_keypair_response.py
huaweicloudsdkkps/v3/model/clear_private_key_request.py
huaweicloudsdkkps/v3/model/clear_private_key_response.py
huaweicloudsdkkps/v3/model/create_keypair_action.py
huaweicloudsdkkps/v3/model/create_keypair_request.py
huaweicloudsdkkps/v3/model/create_keypair_request_body.py
huaweicloudsdkkps/v3/model/create_keypair_resp.py
huaweicloudsdkkps/v3/model/create_keypair_response.py
huaweicloudsdkkps/v3/model/create_keypair_response_body.py
huaweicloudsdkkps/v3/model/delete_all_failed_task_request.py
huaweicloudsdkkps/v3/model/delete_all_failed_task_response.py
huaweicloudsdkkps/v3/model/delete_failed_task_request.py
huaweicloudsdkkps/v3/model/delete_failed_task_response.py
huaweicloudsdkkps/v3/model/delete_keypair_request.py
huaweicloudsdkkps/v3/model/delete_keypair_response.py
huaweicloudsdkkps/v3/model/disassociate_ecs_server_info.py
huaweicloudsdkkps/v3/model/disassociate_keypair_request.py
huaweicloudsdkkps/v3/model/disassociate_keypair_request_body.py
huaweicloudsdkkps/v3/model/disassociate_keypair_response.py
huaweicloudsdkkps/v3/model/ecs_server_info.py
huaweicloudsdkkps/v3/model/encryption.py
huaweicloudsdkkps/v3/model/export_private_key_keypair_bean.py
huaweicloudsdkkps-3.1.184.dist-info/METADATA
huaweicloudsdkkps-3.1.184.dist-info/WHEEL
huaweicloudsdkkps-3.1.184.dist-info/licenses/LICENSE
huaweicloudsdkkps-3.1.184.dist-info/RECORD
